sqlgen.py
sqlgen-0.1.13.dist-info/LICENSE
sqlgen-0.1.13.dist-info/METADATA
sqlgen-0.1.13.dist-info/WHEEL
sqlgen-0.1.13.dist-info/top_level.txt
sqlgen-0.1.13.dist-info/RECORD
